{
  "_id": "323f7d11baa4464489129fe6be0c6f67",
  "Name": "王夫之",
  "Description": "",
  "Dynasty": "清代",
  "Birth": "",
  "Death": "",
  "Poems": [
    {
      "_id": null,
      "Name": "杂诗",
      "PoetId": "323f7d11baa4464489129fe6be0c6f67",
      "PoetName": "王夫之",
      "Form": "未知",
      "Tags": [
        "清代",
        "王夫之"
      ],
      "Contents": [
        "悲风动中夜，",
        "边马嘶且惊。",
        "壮士匣中刀，",
        "犹作风雨鸣。",
        "飞将不见期，",
        "萧条阴北征。",
        "关河空杳霭，",
        "烟草转纵横。",
        "披衣视良夜，",
        "河汉已西倾。",
        "国忧今未释，",
        "何用慰平生。"
      ]
    }
  ]
}