{
  "_id": "25f202d5de9747328228409b3794f236",
  "Name": "安守范",
  "Description": "",
  "Dynasty": "唐代",
  "Birth": "",
  "Death": "",
  "Poems": [
    {
      "_id": null,
      "Name": "天台禅院联句",
      "PoetId": "25f202d5de9747328228409b3794f236",
      "PoetName": "安守范",
      "Form": "未知",
      "Tags": [
        "唐代",
        "安守范"
      ],
      "Contents": [
        "偶到天台院，",
        "因逢物外僧。",
        "--安守范忘机同一祖，",
        "出语离三乘。",
        "--杨鼎夫树老中庭寂，",
        "窗虚外境澄。",
        "--周述片时松影下，",
        "联续百千灯。",
        "--李仁肇"
      ]
    }
  ]
}