{
  "_id": "c85204ad314f45e9aba86000b3ed0ecb",
  "Name": "清尚",
  "Description": "",
  "Dynasty": "唐代",
  "Birth": "",
  "Death": "",
  "Poems": [
    {
      "_id": null,
      "Name": "哭僧",
      "PoetId": "c85204ad314f45e9aba86000b3ed0ecb",
      "PoetName": "清尚",
      "Form": "五律",
      "Tags": [
        "唐代",
        "清尚"
      ],
      "Contents": [
        "道力自超然，",
        "身亡同坐禅。",
        "水流元在海，",
        "月落不离天。",
        "溪白葬时雪，",
        "风香焚处烟。",
        "世人频下泪，",
        "不见我师玄。"
      ]
    }
  ]
}