{
  "_id": "34517e828187471eb8f81288655d1566",
  "Name": "王仲舒",
  "Description": "王仲舒，字弘中，并州祁人。少客江南，与梁肃、杨凭游，并有文名。元和初，为职方郎中、知制诰。穆宗初，为中书舍人。终江南西道观察使。诗一首。",
  "Dynasty": "唐代",
  "Birth": "",
  "Death": "",
  "Poems": [
    {
      "_id": null,
      "Name": "寄李十员外",
      "PoetId": "34517e828187471eb8f81288655d1566",
      "PoetName": "王仲舒",
      "Form": "七绝",
      "Tags": [
        "唐代",
        "王仲舒"
      ],
      "Contents": [
        "百丈悬泉旧卧龙，",
        "欲将肝胆佐时雍。",
        "惟愁又入烟霞去，",
        "知在庐峰第几重。"
      ]
    }
  ]
}