{
  "_id": "184bdff15c0c4c2a97609bb84bd3d20b",
  "Name": "王勔",
  "Description": "王勔，勃之兄也。累官泾州刺史。诗一首。",
  "Dynasty": "唐代",
  "Birth": "",
  "Death": "",
  "Poems": [
    {
      "_id": null,
      "Name": "晦日宴高氏林亭同用华字",
      "PoetId": "184bdff15c0c4c2a97609bb84bd3d20b",
      "PoetName": "王勔",
      "Form": "未知",
      "Tags": [
        "唐代",
        "王勔"
      ],
      "Contents": [
        "上序披林馆，",
        "中京视物华。",
        "竹窗低露叶，",
        "梅径起风花。",
        "景落春台雾，",
        "池侵旧渚沙。",
        "绮筵歌吹晚，",
        "幕雨泛香车。",
        "第五十七卷"
      ]
    }
  ]
}