{
  "_id": "df2edfe6921245e5a69a782d30aa88e0",
  "Name": "赵存约",
  "Description": "赵存约，长庆进士。太和中，为兴元节度判官，兵乱被害。诗一首。",
  "Dynasty": "唐代",
  "Birth": "",
  "Death": "",
  "Poems": [
    {
      "_id": null,
      "Name": "鸟散余花落",
      "PoetId": "df2edfe6921245e5a69a782d30aa88e0",
      "PoetName": "赵存约",
      "Form": "未知",
      "Tags": [
        "唐代",
        "赵存约"
      ],
      "Contents": [
        "春晓游禽集，",
        "幽庭几树花。",
        "坐来惊艳色，",
        "飞去堕晴霞。",
        "翅拂繁枝落，",
        "风添舞影斜。",
        "彩云飘玉砌，",
        "绛雪下仙家。",
        "分散音初静，",
        "凋零蕊带葩。",
        "空阶瞻玩久，",
        "应共惜年华。"
      ]
    }
  ]
}