{
  "_id": "91d5637ad38546ffba00d3de193b5e00",
  "Name": "路洵美",
  "Description": "路洵美，永州祁阳人，唐相岩之孙。避地湘潭，事马氏，署连州从事。诗一首。",
  "Dynasty": "唐代",
  "Birth": "",
  "Death": "",
  "Poems": [
    {
      "_id": null,
      "Name": "夜坐",
      "PoetId": "91d5637ad38546ffba00d3de193b5e00",
      "PoetName": "路洵美",
      "Form": "五律",
      "Tags": [
        "唐代",
        "路洵美"
      ],
      "Contents": [
        "帘卷竹轩清，",
        "四邻无语声。",
        "漏从吟里转，",
        "月自坐来明。",
        "草木露华湿，",
        "衣裳寒气生。",
        "难逢知鉴者，",
        "空悦此时情。"
      ]
    }
  ]
}