{
  "_id": "062e2f7833a449b2ac35799411c8b0f3",
  "Name": "路贯",
  "Description": "路贯，与元晦同登第，官桂管观察副使。诗一首。",
  "Dynasty": "唐代",
  "Birth": "",
  "Death": "",
  "Poems": [
    {
      "_id": null,
      "Name": "和元常侍除浙东留题",
      "PoetId": "062e2f7833a449b2ac35799411c8b0f3",
      "PoetName": "路贯",
      "Form": "七律",
      "Tags": [
        "唐代",
        "路贯"
      ],
      "Contents": [
        "谢安致理逾三载，",
        "黄霸清声彻九重。",
        "犹辍珮环归凤阙，",
        "且将仁政到稽峰。",
        "林间立马罗千骑，",
        "池上开筵醉一钟。",
        "共喜甘棠有新咏，",
        "独惭霜鬓又攀龙。"
      ]
    }
  ]
}