{
  "_id": "9fd88ce4794a4d5b9e6353cf5bc74c76",
  "Name": "陆岩梦",
  "Description": "",
  "Dynasty": "唐代",
  "Birth": "",
  "Death": "",
  "Poems": [
    {
      "_id": null,
      "Name": "桂州筵上赠胡予女",
      "PoetId": "9fd88ce4794a4d5b9e6353cf5bc74c76",
      "PoetName": "陆岩梦",
      "Form": "七律",
      "Tags": [
        "唐代",
        "陆岩梦"
      ],
      "Contents": [
        "自道风流不可攀，",
        "却堪蹙额更颓颜。",
        "眼睛深却湘江水，",
        "鼻孔高于华岳山。",
        "舞态固难居掌上，",
        "歌声应不绕梁间。",
        "孟阳死后欲千载，",
        "犹在佳人觅往还。"
      ]
    }
  ]
}