{
  "_id": "faf20cb341de4bf3a5cd3376e3adf42e",
  "Name": "姚宽",
  "Description": "",
  "Dynasty": "宋代",
  "Birth": "",
  "Death": "",
  "Poems": [
    {
      "_id": null,
      "Name": "怨王孙·忆王孙",
      "PoetId": "faf20cb341de4bf3a5cd3376e3adf42e",
      "PoetName": "姚宽",
      "Form": "词",
      "Tags": [
        "宋代",
        "姚宽"
      ],
      "Contents": [
        "毵毵杨柳绿初低。",
        "澹澹梨花开未齐。",
        "楼上情人听马嘶。",
        "忆郎归。",
        "细雨春风湿酒旗。"
      ]
    },
    {
      "_id": null,
      "Name": "生查子",
      "PoetId": "faf20cb341de4bf3a5cd3376e3adf42e",
      "PoetName": "姚宽",
      "Form": "五律",
      "Tags": [
        "宋代",
        "姚宽"
      ],
      "Contents": [
        "郎如陌上尘，",
        "妾似堤边絮。",
        "相见两悠扬，",
        "踪迹无寻处。",
        "酒面扑春风，",
        "泪眼零秋雨。",
        "过了离别时，",
        "还解相思否？"
      ]
    },
    {
      "_id": null,
      "Name": "菩萨蛮",
      "PoetId": "faf20cb341de4bf3a5cd3376e3adf42e",
      "PoetName": "姚宽",
      "Form": "词",
      "Tags": [
        "宋代",
        "姚宽"
      ],
      "Contents": [
        "斜阳山下明金碧。",
        "画楼返照融春色。",
        "睡起揭帘旌。",
        "玉人蝉鬓轻。",
        "无言空伫立。",
        "花落东风急。",
        "燕子引愁来。",
        "眉心那得开。"
      ]
    },
    {
      "_id": null,
      "Name": "踏莎行",
      "PoetId": "faf20cb341de4bf3a5cd3376e3adf42e",
      "PoetName": "姚宽",
      "Form": "词",
      "Tags": [
        "宋代",
        "姚宽"
      ],
      "Contents": [
        "苹页烟深，",
        "荷花露湿。",
        "碧芦红蓼秋风急。",
        "采菱渡口日将沈，",
        "飞鸿楼上人空立。",
        "彩凤难双，",
        "红绡暗泣。",
        "回纹未剪吴刀涩。",
        "梦云归处不留踪，",
        "厌厌一夜凉蟾入。"
      ]
    }
  ]
}