{
  "_id": "e94f592ac0ea4940832969b103d35ef7",
  "Name": "杨师纯",
  "Description": "",
  "Dynasty": "宋代",
  "Birth": "",
  "Death": "",
  "Poems": [
    {
      "_id": null,
      "Name": "清平乐",
      "PoetId": "e94f592ac0ea4940832969b103d35ef7",
      "PoetName": "杨师纯",
      "Form": "词",
      "Tags": [
        "宋代",
        "杨师纯"
      ],
      "Contents": [
        "小庭春院。",
        "睡起花阴转。",
        "往事旧欢离思远。",
        "柳絮随风难管。",
        "等闲屈指当时。",
        "阑干几曲谁知。",
        "为问春风桃李，",
        "而今子满芳枝。"
      ]
    }
  ]
}