{
  "_id": "afc45294be3f4564b7998017cf61685c",
  "Name": "王玉",
  "Description": "",
  "Dynasty": "宋代",
  "Birth": "",
  "Death": "",
  "Poems": [
    {
      "_id": null,
      "Name": "朝中措",
      "PoetId": "afc45294be3f4564b7998017cf61685c",
      "PoetName": "王玉",
      "Form": "词",
      "Tags": [
        "宋代",
        "王玉"
      ],
      "Contents": [
        "杨花绕昼暖风多。",
        "晴云点池波。",
        "戏数翠萍几靥，",
        "零星未碍圆荷。",
        "软人天气，",
        "半如溽暑，",
        "半似清和。",
        "说与香篝緼火，",
        "酒痕梅却衣罗。"
      ]
    }
  ]
}