{
  "_id": "83d47259fd194b4d99c401d681852421",
  "Name": "顾卞",
  "Description": "",
  "Dynasty": "宋代",
  "Birth": "",
  "Death": "",
  "Poems": [
    {
      "_id": null,
      "Name": "虞美人",
      "PoetId": "83d47259fd194b4d99c401d681852421",
      "PoetName": "顾卞",
      "Form": "词",
      "Tags": [
        "宋代",
        "顾卞"
      ],
      "Contents": [
        "帐前草草军情变。",
        "月下旗旌乱。",
        "褫衣推枕惜离情。",
        "远风吹下楚歌声。",
        "正三更。",
        "抚鞍欲上重相顾。",
        "艳态花无主。",
        "手中莲萼凛秋霜。",
        "九泉归路是仙乡。",
        "恨茫茫。"
      ]
    }
  ]
}