{
  "_id": "33ede8ea5bf24ba8bc6b16e6903b6b15",
  "Name": "冯子翼",
  "Description": "",
  "Dynasty": "元代",
  "Birth": "",
  "Death": "",
  "Poems": [
    {
      "_id": null,
      "Name": "江城子",
      "PoetId": "33ede8ea5bf24ba8bc6b16e6903b6b15",
      "PoetName": "冯子翼",
      "Form": "词",
      "Tags": [
        "元代",
        "冯子翼"
      ],
      "Contents": [
        "胭脂坡上月如钩。",
        "问青楼。",
        "觅温柔。",
        "庭院深沈，",
        "窗户掩清秋。",
        "月下香云娇堕砌，",
        "花气重，",
        "酒光浮。",
        "清歌皓齿艳明眸。",
        "锦缠头。",
        "若为酬。",
        "门外三更，",
        "灯影立骅骝。",
        "结习未忘吾老矣。",
        "烦恼梦，",
        "赴东流。"
      ]
    }
  ]
}