{
  "_id": "cc9b183ae38e411794e0274bbd045eb1",
  "Name": "陈益之",
  "Description": "",
  "Dynasty": "元代",
  "Birth": "",
  "Death": "",
  "Poems": [
    {
      "_id": null,
      "Name": "贺新郎",
      "PoetId": "cc9b183ae38e411794e0274bbd045eb1",
      "PoetName": "陈益之",
      "Form": "词",
      "Tags": [
        "元代",
        "陈益之"
      ],
      "Contents": [
        "满酌开怀酒。",
        "算人生、不如意事，",
        "十常八九。",
        "造化小儿真厮戏，",
        "到了翻前覆后。",
        "谩只向、尘中奔走。",
        "多满时贤口。"
      ]
    }
  ]
}