{
  "_id": "70ba5e96d3444642b89c9cfae7a6d4b5",
  "name": "循吏曲上王使君",
  "contents": [
    "需宿需宿，",
    "炳烂光合。",
    "蒸蒸婺民，",
    "钟此多福。",
    "自东自西，",
    "自南自北。",
    "伊飞伊走，",
    "乳乳良牧。",
    "和气无形，",
    "春光自成。",
    "大信不信，",
    "贻厥无朕。",
    "需女需女，",
    "尔亦须语。",
    "使君为理，",
    "玄风震古。",
    "需女需女，",
    "尔亦须语。",
    "我愿喙长三千里，",
    "枕著玉阶奏明主。"
  ],
  "ptype": null,
  "poetName": "贯休",
  "poetId": "2010d2499c414e5c920b044c4657b2cb",
  "form": "未知",
  "tags": [
    "06.唐代",
    "贯休",
    ""
  ]
}